[
    {
      "username": "Brian Kernighan",
      "password": "password01"
    },
    {
      "username": "Max Kanat-Alexander",
      "password": "password02"
    },
    {
      "username": "Amiko",
      "password": "password03"
    },
    {
      "username": "Kent Beck",
      "password": "password04"
    },
    {
      "username": "Edward V. Berard",
      "password": "password05"
    },
    {
      "username": "Alan Kay",
      "password": "password06"
    },
    {
      "username": "C.A.R. Hoare",
      "password": "password07"
    },
    {
      "username": "David Thomas",
      "password": "password08"
    },
    {
      "username": "Donald Knuth",
      "password": "password09"
    },
    {
      "username": "Lernantino",
      "password": "password10"
    }
  ]
  